CMakeLists.txt
LICENSE
MANIFEST.in
README.md
setup.py
CMake/FindRocksDB.cmake
CMake/Findpybind11.cmake
CMake/PreventInSourceBuild.cmake
Rocksdb_python.egg-info/PKG-INFO
Rocksdb_python.egg-info/SOURCES.txt
Rocksdb_python.egg-info/dependency_links.txt
Rocksdb_python.egg-info/top_level.txt
rocksdb/__init__.py
rocksdb/client.py
rocksdb/options.py
rocksdb/ext/extension.cpp
rocksdb/ext/rocksdb.hpp
rocksdb/ext/pybind11/.appveyor.yml
rocksdb/ext/pybind11/.clang-format
rocksdb/ext/pybind11/.clang-tidy
rocksdb/ext/pybind11/.cmake-format.yaml
rocksdb/ext/pybind11/.codespell-ignore-lines
rocksdb/ext/pybind11/.git
rocksdb/ext/pybind11/.gitattributes
rocksdb/ext/pybind11/.gitignore
rocksdb/ext/pybind11/.pre-commit-config.yaml
rocksdb/ext/pybind11/.readthedocs.yml
rocksdb/ext/pybind11/CMakeLists.txt
rocksdb/ext/pybind11/LICENSE
rocksdb/ext/pybind11/MANIFEST.in
rocksdb/ext/pybind11/README.rst
rocksdb/ext/pybind11/noxfile.py
rocksdb/ext/pybind11/pyproject.toml
rocksdb/ext/pybind11/setup.cfg
rocksdb/ext/pybind11/setup.py
rocksdb/ext/pybind11/.github/CODEOWNERS
rocksdb/ext/pybind11/.github/CONTRIBUTING.md
rocksdb/ext/pybind11/.github/dependabot.yml
rocksdb/ext/pybind11/.github/labeler.yml
rocksdb/ext/pybind11/.github/labeler_merged.yml
rocksdb/ext/pybind11/.github/pull_request_template.md
rocksdb/ext/pybind11/.github/ISSUE_TEMPLATE/bug-report.yml
rocksdb/ext/pybind11/.github/ISSUE_TEMPLATE/config.yml
rocksdb/ext/pybind11/.github/matchers/pylint.json
rocksdb/ext/pybind11/.github/workflows/ci.yml
rocksdb/ext/pybind11/.github/workflows/configure.yml
rocksdb/ext/pybind11/.github/workflows/format.yml
rocksdb/ext/pybind11/.github/workflows/labeler.yml
rocksdb/ext/pybind11/.github/workflows/pip.yml
rocksdb/ext/pybind11/.github/workflows/upstream.yml
rocksdb/ext/pybind11/docs/Doxyfile
rocksdb/ext/pybind11/docs/Makefile
rocksdb/ext/pybind11/docs/basics.rst
rocksdb/ext/pybind11/docs/benchmark.py
rocksdb/ext/pybind11/docs/benchmark.rst
rocksdb/ext/pybind11/docs/changelog.rst
rocksdb/ext/pybind11/docs/classes.rst
rocksdb/ext/pybind11/docs/compiling.rst
rocksdb/ext/pybind11/docs/conf.py
rocksdb/ext/pybind11/docs/faq.rst
