Metadata-Version: 2.1
Name: Rocksdb-python
Version: 0.1.2
Summary: Simple and easy rocksdb client for python
Home-page: https://github.com/AYMENJD/rocksdb-python
Author: AYMEN Mohammed
Author-email: let.me.code.safe@gmail.com
License: MIT
Project-URL: Source, https://github.com/AYMENJD/rocksdb-python
Project-URL: Tracker, https://github.com/AYMENJD/rocksdb-python/issues
Project-URL: Documantation, https://github.com/AYMENJD/rocksdb-python/wiki
Keywords: rocksdb,database,async,python,pybind11
Platform: UNKNOWN
Requires-Python: >=3.8
License-File: LICENSE
